Workbook

Sheet Dashboard
A1: FutureNest 30-Day Validation Dashboard
A3: Start date | B3: 2026-08-25 | D3: End date | E3: 2026-09-23 | G3: Website | H3: future.lumicore-labs.com
A5: Overall Progress
A6: Total tasks | B6: =COUNTA(Tasks!$A$2:$A$193) | C6: Completed | D6: =COUNTIF(Tasks!$F$2:$F$193,"☑") | E6: Remaining | F6: =B6-D6 | G6: Completion % | H6: =IFERROR(D6/B6,0)
A9: Progress by Day
A10: Day | B10: Date | C10: Focus | D10: Total | E10: Done | F10: Remaining | G10: Progress
A11: 1 | B11: 2026-08-25 | C11: Create the Repository | D11: =COUNTIF(Tasks!$A$2:$A$193,A11) | E11: =COUNTIFS(Tasks!$A$2:$A$193,A11,Tasks!$F$2:$F$193,"☑") | F11: =D11-E11 | G11: =IFERROR(E11/D11,0)
A12: 2 | B12: 2026-08-26 | C12: DNS and VPS Preparation | D12: =COUNTIF(Tasks!$A$2:$A$193,A12) | E12: =COUNTIFS(Tasks!$A$2:$A$193,A12,Tasks!$F$2:$F$193,"☑") | F12: =D12-E12 | G12: =IFERROR(E12/D12,0)
A13: 3 | B13: 2026-08-27 | C13: First Deployment | D13: =COUNTIF(Tasks!$A$2:$A$193,A13) | E13: =COUNTIFS(Tasks!$A$2:$A$193,A13,Tasks!$F$2:$F$193,"☑") | F13: =D13-E13 | G13: =IFERROR(E13/D13,0)
A14: 4 | B14: 2026-08-28 | C14: MVP Scope and Site Skeleton | D14: =COUNTIF(Tasks!$A$2:$A$193,A14) | E14: =COUNTIFS(Tasks!$A$2:$A$193,A14,Tasks!$F$2:$F$193,"☑") | F14: =D14-E14 | G14: =IFERROR(E14/D14,0)
A15: 5 | B15: 2026-08-29 | C15: Affiliate Research and Applications | D15: =COUNTIF(Tasks!$A$2:$A$193,A15) | E15: =COUNTIFS(Tasks!$A$2:$A$193,A15,Tasks!$F$2:$F$193,"☑") | F15: =D15-E15 | G15: =IFERROR(E15/D15,0)
A16: 6 | B16: 2026-08-30 | C16: Tracking Design | D16: =COUNTIF(Tasks!$A$2:$A$193,A16) | E16: =COUNTIFS(Tasks!$A$2:$A$193,A16,Tasks!$F$2:$F$193,"☑") | F16: =D16-E16 | G16: =IFERROR(E16/D16,0)
A17: 7 | B17: 2026-08-31 | C17: Week 1 Review | D17: =COUNTIF(Tasks!$A$2:$A$193,A17) | E17: =COUNTIFS(Tasks!$A$2:$A$193,A17,Tasks!$F$2:$F$193,"☑") | F17: =D17-E17 | G17: =IFERROR(E17/D17,0)
A18: 8 | B18: 2026-09-01 | C18: Homepage | D18: =COUNTIF(Tasks!$A$2:$A$193,A18) | E18: =COUNTIFS(Tasks!$A$2:$A$193,A18,Tasks!$F$2:$F$193,"☑") | F18: =D18-E18 | G18: =IFERROR(E18/D18,0)
A19: 9 | B19: 2026-09-02 | C19: Article One | D19: =COUNTIF(Tasks!$A$2:$A$193,A19) | E19: =COUNTIFS(Tasks!$A$2:$A$193,A19,Tasks!$F$2:$F$193,"☑") | F19: =D19-E19 | G19: =IFERROR(E19/D19,0)
A20: 10 | B20: 2026-09-03 | C20: Article Two | D20: =COUNTIF(Tasks!$A$2:$A$193,A20) | E20: =COUNTIFS(Tasks!$A$2:$A$193,A20,Tasks!$F$2:$F$193,"☑") | F20: =D20-E20 | G20: =IFERROR(E20/D20,0)
A21: 11 | B21: 2026-09-04 | C21: Inspiration Article | D21: =COUNTIF(Tasks!$A$2:$A$193,A21) | E21: =COUNTIFS(Tasks!$A$2:$A$193,A21,Tasks!$F$2:$F$193,"☑") | F21: =D21-E21 | G21: =IFERROR(E21/D21,0)
A22: 12 | B22: 2026-09-05 | C22: Legal and SEO Basics | D22: =COUNTIF(Tasks!$A$2:$A$193,A22) | E22: =COUNTIFS(Tasks!$A$2:$A$193,A22,Tasks!$F$2:$F$193,"☑") | F22: =D22-E22 | G22: =IFERROR(E22/D22,0)
... A40: 30 | B40: 2026-09-23 | C40: Close the Experiment | D40: =COUNTIF(Tasks!$A$2:$A$193,A40) | E40: =COUNTIFS(Tasks!$A$2:$A$193,A40,Tasks!$F$2:$F$193,"☑") | F40: =D40-E40 | G40: =IFERROR(E40/D40,0)
A44: Progress by Priority
A45: Priority | B45: Total | C45: Done | D45: Remaining | E45: Progress
A46: Must do | B46: =COUNTIF(Tasks!$D$2:$D$193,A46) | C46: =COUNTIFS(Tasks!$D$2:$D$193,A46,Tasks!$F$2:$F$193,"☑") | D46: =B46-C46 | E46: =IFERROR(C46/B46,0)
A47: Should do | B47: =COUNTIF(Tasks!$D$2:$D$193,A47) | C47: =COUNTIFS(Tasks!$D$2:$D$193,A47,Tasks!$F$2:$F$193,"☑") | D47: =B47-C47 | E47: =IFERROR(C47/B47,0)
A48: Optional | B48: =COUNTIF(Tasks!$D$2:$D$193,A48) | C48: =COUNTIFS(Tasks!$D$2:$D$193,A48,Tasks!$F$2:$F$193,"☑") | D48: =B48-C48 | E48: =IFERROR(C48/B48,0)

Sheet Tasks
A1: Day | B1: Date | C1: Focus | D1: Priority | E1: Task | F1: Done | G1: Notes
A2: 1 | B2: 2026-08-25 | C2: Create the Repository | D2: Must do | E2: Create a future-nest folder inside the current workspace. | F2: ☐
A3: 1 | B3: 2026-08-25 | C3: Create the Repository | D3: Must do | E3: Initialize future-nest as a separate Git repository. | F3: ☐
A4: 1 | B4: 2026-08-25 | C4: Create the Repository | D4: Must do | E4: Create the Nuxt project using the current stable Nuxt setup. | F4: ☐
A5: 1 | B5: 2026-08-25 | C5: Create the Repository | D5: Must do | E5: Confirm the project runs locally. | F5: ☐
A6: 1 | B6: 2026-08-25 | C6: Create the Repository | D6: Must do | E6: Add a README with the project purpose and deployment target. | F6: ☐
A7: 1 | B7: 2026-08-25 | C7: Create the Repository | D7: Must do | E7: Add .env.example and confirm secrets are ignored. | F7: ☐
A8: 1 | B8: 2026-08-25 | C8: Create the Repository | D8: Should do | E8: Create folders for pages, content, data, assets, and components. | F8: ☐
A9: 1 | B9: 2026-08-25 | C9: Create the Repository | D9: Should do | E9: Add a simple homepage placeholder and make the first local commit. | F9: ☐
A10: 1 | B10: 2026-08-25 | C10: Create the Repository | D10: Optional | E10: Create the remote repository and push the initial commit. | F10: ☐
A11: 2 | B11: 2026-08-26 | C11: DNS and VPS Preparation | D11: Must do | E11: Add the future A record for lumicore-labs.com pointing to the VPS IP. | F11: ☐
A12: 2 | B12: 2026-08-26 | C12: DNS and VPS Preparation | D12: Must do | E12: Verify DNS with nslookup. | F12: ☐
A13: 2 | B13: 2026-08-26 | C13: DNS and VPS Preparation | D13: Must do | E13: Create /var/www/future-nest on the VPS. | F13: ☐
... A193: 30 | B193: 2026-09-23 | C193: Close the Experiment | D193: Optional | E193: Create the next daily plan only after the decision is approved. | F193: ☐

Sheet Instructions
A1: How to Use This Workbook
A3: 1 | B3: Open the Tasks sheet and use the Done dropdown for each task.
A4: 2 | B4: Choose ☐ for incomplete or ☑ for complete.
A5: 3 | B5: Add blockers, links, or evidence in the Notes column.
A6: 4 | B6: The Dashboard updates when Excel recalculates formulas.
A7: 5 | B7: Filter Tasks by day, focus, or priority when planning a work block.
A8: 6 | B8: Regenerate the workbook after changing the source CSV; manual checkbox progress will not be preserved.
